{
	"metaDataVersion": "1.0.0",
	"category": "com.microchip.ide.project",
	"content": {
		"metaDataVersion": "1.1.0",
		"name": "com.microchip.mcu32.mplabx.project.csp_apps_pic32cxbz2_wbz45_rtc_alarm",
		"version": "3.1.0",
		"displayName": "RTC alarm interrupt Example for PIC32CX-BZ2 Family",
		"projectName": "rtc_alarm_wbz451_curiosity",
		"shortDescription": "This example shows how to use the RTC to configure the time and generate the alarm.",
		"ide": {
			"name": "MPLABX",
			"semverRange": ">=6.5.0"
		},
		"compiler": [
			{
				"name": "XC32",
				"semverRange": ">=4.21.0"
			}
		],
		"dfp": {
			"name": "PIC32CX-BZ_DFP",
			"semverRange": "^1.0.107"
		},
		"configurator": {
			"name": "MCC",
			"semverRange": ">=5.3.0"
		},
		"device": {
			"metaDataVersion": "1.0.0",
			"category": "com.microchip.portal.contentRef",
			"content": {
				"metaDataVersion": "1.0.0",
				"category": "com.microchip.device",
				"name": "WBZ451",
				"versionRange": "*"
			}
		},
		"author": "Microchip",
		"subcategories": [
			[
				"Development Kit",
				"PIC32CX WBZ451 Curiosity Board"
			],
			[
				"Harmony",
				"Peripherals",
				"RTC"
			],
			[
				"Peripherals",
				"RTC"
			]
		],
		"peripherals": [
			"RTC"
		],
		"keywords": [
			"MHC",
			"Harmony",
			"WBZ451",
			"PIC32CX-BZ2 Family",
			"RTC",
			"RTT",
			"RTCC",
			"Timer",
			"Real Time Counter"
		],
		"additionalData": {
			"longDescription": {
				"metaDataVersion": "1.0.0",
				"category": "com.microchip.portal.fileRef",
				"content": {
					"metaDataVersion": "1.0.0",
					"fileName": "./../../readme.md",
					"mimeType": "text/markdown"
				}
			}
		}
	}
}